{"object": "card", "id": "dc457520-9947-4f65-bbe7-9b95bd2c23af", "oracle_id": "19b229c4-1c21-4c7c-a25e-4e8c1cd4ed4b", "multiverse_ids": [527333], "mtgo_id": 91594, "arena_id": 77151, "tcgplayer_id": 243275, "cardmarket_id": 571399, "name": "Arcane Investigator", "lang": "en", "released_at": "2021-07-23", "uri": "https://api.scryfall.com/cards/dc457520-9947-4f65-bbe7-9b95bd2c23af", "scryfall_uri": "https://scryfall.com/card/afr/46/arcane-investigator?utm_source=api", "layout": "normal", "highres_image": true, "image_status": "highres_scan", "image_uris": {"small": "https://cards.scryfall.io/small/front/d/c/dc457520-9947-4f65-bbe7-9b95bd2c23af.jpg?1627702826", "normal": "https://cards.scryfall.io/normal/front/d/c/dc457520-9947-4f65-bbe7-9b95bd2c23af.jpg?1627702826", "large": "https://cards.scryfall.io/large/front/d/c/dc457520-9947-4f65-bbe7-9b95bd2c23af.jpg?1627702826", "png": "https://cards.scryfall.io/png/front/d/c/dc457520-9947-4f65-bbe7-9b95bd2c23af.png?1627702826", "art_crop": "https://cards.scryfall.io/art_crop/front/d/c/dc457520-9947-4f65-bbe7-9b95bd2c23af.jpg?1627702826", "border_crop": "https://cards.scryfall.io/border_crop/front/d/c/dc457520-9947-4f65-bbe7-9b95bd2c23af.jpg?1627702826"}, "mana_cost": "{1}{U}", "cmc": 2.0, "type_line": "Creature \u2014 Elf Wizard", "oracle_text": "Search the Room \u2014 {5}{U}: Roll a d20.\n1\u20149 | Draw a card.\n10\u201420 | Look at the top three cards of your library. Put one of them into your hand and the rest on the bottom of your library in any order.", "power": "2", "toughness": "1", "colors": ["U"], "color_identity": ["U"], "keywords": [], "legalities": {"standard": "not_legal", "future": "not_legal", "historic": "legal", "timeless": "legal", "gladiator": "legal", "pioneer": "legal", "modern": "legal", "legacy": "legal", "pauper": "legal", "vintage": "legal", "penny": "not_legal", "commander": "legal", "oathbreaker": "legal", "standardbrawl": "not_legal", "brawl": "legal", "alchemy": "not_legal", "paupercommander": "legal", "duel": "legal", "oldschool": "not_legal", "premodern": "not_legal", "predh": "not_legal"}, "games": ["arena", "paper", "mtgo"], "reserved": false, "game_changer": false, "foil": true, "nonfoil": true, "finishes": ["nonfoil", "foil"], "oversized": false, "promo": false, "reprint": false, "variation": false, "set_id": "e1ef87ba-ba92-4573-817f-543b996d2851", "set": "afr", "set_name": "Adventures in the Forgotten Realms", "set_type": "expansion", "set_uri": "https://api.scryfall.com/sets/e1ef87ba-ba92-4573-817f-543b996d2851", "set_search_uri": "https://api.scryfall.com/cards/search?order=set&q=e%3Aafr&unique=prints", "scryfall_set_uri": "https://scryfall.com/sets/afr?utm_source=api", "rulings_uri": "https://api.scryfall.com/cards/dc457520-9947-4f65-bbe7-9b95bd2c23af/rulings", "prints_search_uri": "https://api.scryfall.com/cards/search?order=released&q=oracleid%3A19b229c4-1c21-4c7c-a25e-4e8c1cd4ed4b&unique=prints", "collector_number": "46", "digital": false, "rarity": "common", "card_back_id": "0aeebaf5-8c7d-4636-9e82-8c27447861f7", "artist": "Bram Sels", "artist_ids": ["2e90d3c1-e8ac-45c7-9d5a-63385c1a384d"], "illustration_id": "d632af43-7572-4488-a822-6a9b698f1cc0", "border_color": "black", "frame": "2015", "full_art": false, "textless": false, "booster": true, "story_spotlight": false, "edhrec_rank": 14950, "penny_rank": 14316, "prices": {"usd": "0.04", "usd_foil": "0.07", "usd_etched": null, "eur": "0.10", "eur_foil": "0.15", "tix": "0.03"}, "related_uris": {"gatherer": "https://gatherer.wizards.com/Pages/Card/Details.aspx?multiverseid=527333&printed=false", "tcgplayer_infinite_articles": "https://partner.tcgplayer.com/c/4931599/1830156/21018?subId1=api&trafcat=tcgplayer.com%2Fsearch%2Farticles&u=https%3A%2F%2Fwww.tcgplayer.com%2Fsearch%2Farticles%3FproductLineName%3Dmagic%26q%3DArcane%2BInvestigator", "tcgplayer_infinite_decks": "https://partner.tcgplayer.com/c/4931599/1830156/21018?subId1=api&trafcat=tcgplayer.com%2Fsearch%2Fdecks&u=https%3A%2F%2Fwww.tcgplayer.com%2Fsearch%2Fdecks%3FproductLineName%3Dmagic%26q%3DArcane%2BInvestigator", "edhrec": "https://edhrec.com/route/?cc=Arcane+Investigator"}, "purchase_uris": {"tcgplayer": "https://partner.tcgplayer.com/c/4931599/1830156/21018?subId1=api&u=https%3A%2F%2Fwww.tcgplayer.com%2Fproduct%2F243275%3Fpage%3D1", "cardmarket": "https://www.cardmarket.com/en/Magic/Products?idProduct=571399&referrer=scryfall&utm_campaign=card_prices&utm_medium=text&utm_source=scryfall", "cardhoarder": "https://www.cardhoarder.com/cards/91594?affiliate_id=scryfall&ref=card-profile&utm_campaign=affiliate&utm_medium=card&utm_source=scryfall"}}