{"object": "card", "id": "ef04340d-284c-4e7b-afd7-444d21a6b382", "oracle_id": "b9ed0081-7eda-4ff9-ac2d-bcdc29a22d9f", "multiverse_ids": [489298], "arena_id": 72203, "tcgplayer_id": 216532, "cardmarket_id": 474334, "name": "Belltower Sphinx", "lang": "en", "released_at": "2020-07-17", "uri": "https://api.scryfall.com/cards/ef04340d-284c-4e7b-afd7-444d21a6b382", "scryfall_uri": "https://scryfall.com/card/jmp/141/belltower-sphinx?utm_source=api", "layout": "normal", "highres_image": true, "image_status": "highres_scan", "image_uris": {"small": "https://cards.scryfall.io/small/front/e/f/ef04340d-284c-4e7b-afd7-444d21a6b382.jpg?1600724884", "normal": "https://cards.scryfall.io/normal/front/e/f/ef04340d-284c-4e7b-afd7-444d21a6b382.jpg?1600724884", "large": "https://cards.scryfall.io/large/front/e/f/ef04340d-284c-4e7b-afd7-444d21a6b382.jpg?1600724884", "png": "https://cards.scryfall.io/png/front/e/f/ef04340d-284c-4e7b-afd7-444d21a6b382.png?1600724884", "art_crop": "https://cards.scryfall.io/art_crop/front/e/f/ef04340d-284c-4e7b-afd7-444d21a6b382.jpg?1600724884", "border_crop": "https://cards.scryfall.io/border_crop/front/e/f/ef04340d-284c-4e7b-afd7-444d21a6b382.jpg?1600724884"}, "mana_cost": "{4}{U}", "cmc": 5.0, "type_line": "Creature \u2014 Sphinx", "oracle_text": "Flying\nWhenever a source deals damage to this creature, that source's controller mills that many cards.", "power": "2", "toughness": "5", "colors": ["U"], "color_identity": ["U"], "keywords": ["Flying", "Mill"], "legalities": {"standard": "not_legal", "future": "not_legal", "historic": "legal", "timeless": "legal", "gladiator": "legal", "pioneer": "not_legal", "modern": "legal", "legacy": "legal", "pauper": "not_legal", "vintage": "legal", "penny": "legal", "commander": "legal", "oathbreaker": "legal", "standardbrawl": "not_legal", "brawl": "legal", "alchemy": "not_legal", "paupercommander": "not_legal", "duel": "legal", "oldschool": "not_legal", "premodern": "not_legal", "predh": "legal"}, "games": ["arena", "paper"], "reserved": false, "game_changer": false, "foil": false, "nonfoil": true, "finishes": ["nonfoil"], "oversized": false, "promo": false, "reprint": true, "variation": false, "set_id": "0f6ccf25-a627-4263-86df-5757137f1696", "set": "jmp", "set_name": "Jumpstart", "set_type": "draft_innovation", "set_uri": "https://api.scryfall.com/sets/0f6ccf25-a627-4263-86df-5757137f1696", "set_search_uri": "https://api.scryfall.com/cards/search?order=set&q=e%3Ajmp&unique=prints", "scryfall_set_uri": "https://scryfall.com/sets/jmp?utm_source=api", "rulings_uri": "https://api.scryfall.com/cards/ef04340d-284c-4e7b-afd7-444d21a6b382/rulings", "prints_search_uri": "https://api.scryfall.com/cards/search?order=released&q=oracleid%3Ab9ed0081-7eda-4ff9-ac2d-bcdc29a22d9f&unique=prints", "collector_number": "141", "digital": false, "rarity": "uncommon", "card_back_id": "0aeebaf5-8c7d-4636-9e82-8c27447861f7", "artist": "Jim Nelson", "artist_ids": ["aa9f64d1-29e1-4c82-877e-44c18183f40b"], "illustration_id": "f11ab2b5-8326-42e7-b086-4c1b486a93e1", "border_color": "black", "frame": "2015", "full_art": false, "textless": false, "booster": true, "story_spotlight": false, "edhrec_rank": 18799, "penny_rank": 15479, "preview": {"source": "AfterOfficeTTV", "source_uri": "https://www.twitch.tv/videos/655730487", "previewed_at": "2020-06-19"}, "prices": {"usd": "0.10", "usd_foil": null, "usd_etched": null, "eur": "0.16", "eur_foil": null, "tix": null}, "related_uris": {"gatherer": "https://gatherer.wizards.com/Pages/Card/Details.aspx?multiverseid=489298&printed=false", "tcgplayer_infinite_articles": "https://partner.tcgplayer.com/c/4931599/1830156/21018?subId1=api&trafcat=tcgplayer.com%2Fsearch%2Farticles&u=https%3A%2F%2Fwww.tcgplayer.com%2Fsearch%2Farticles%3FproductLineName%3Dmagic%26q%3DBelltower%2BSphinx", "tcgplayer_infinite_decks": "https://partner.tcgplayer.com/c/4931599/1830156/21018?subId1=api&trafcat=tcgplayer.com%2Fsearch%2Fdecks&u=https%3A%2F%2Fwww.tcgplayer.com%2Fsearch%2Fdecks%3FproductLineName%3Dmagic%26q%3DBelltower%2BSphinx", "edhrec": "https://edhrec.com/route/?cc=Belltower+Sphinx"}, "purchase_uris": {"tcgplayer": "https://partner.tcgplayer.com/c/4931599/1830156/21018?subId1=api&u=https%3A%2F%2Fwww.tcgplayer.com%2Fproduct%2F216532%3Fpage%3D1", "cardmarket": "https://www.cardmarket.com/en/Magic/Products?idProduct=474334&referrer=scryfall&utm_campaign=card_prices&utm_medium=text&utm_source=scryfall", "cardhoarder": "https://www.cardhoarder.com/cards?affiliate_id=scryfall&data%5Bsearch%5D=Belltower+Sphinx&ref=card-profile&utm_campaign=affiliate&utm_medium=card&utm_source=scryfall"}}