{"object": "card", "id": "91664e04-b4e1-4638-8194-6c373ecd02d9", "oracle_id": "0a2995ff-5623-44d7-8620-18f695903d9a", "multiverse_ids": [], "name": "Eriette, the Beguiler // Eriette, the Beguiler", "lang": "en", "released_at": "2024-04-19", "uri": "https://api.scryfall.com/cards/91664e04-b4e1-4638-8194-6c373ecd02d9", "scryfall_uri": "https://scryfall.com/card/aotj/52/eriette-the-beguiler-eriette-the-beguiler?utm_source=api", "layout": "art_series", "highres_image": true, "image_status": "highres_scan", "cmc": 0.0, "type_line": "Card // Card", "color_identity": [], "keywords": [], "card_faces": [{"object": "card_face", "name": "Eriette, the Beguiler", "mana_cost": "", "type_line": "Card", "oracle_text": "", "colors": [], "artist": "Dibujante Nocturno", "artist_id": "ed4f7e1b-4139-4e17-a671-442ce49eb775", "illustration_id": "1222e316-8acc-498b-8334-d078474aab58", "image_uris": {"small": "https://cards.scryfall.io/small/front/9/1/91664e04-b4e1-4638-8194-6c373ecd02d9.jpg?1715954802", "normal": "https://cards.scryfall.io/normal/front/9/1/91664e04-b4e1-4638-8194-6c373ecd02d9.jpg?1715954802", "large": "https://cards.scryfall.io/large/front/9/1/91664e04-b4e1-4638-8194-6c373ecd02d9.jpg?1715954802", "png": "https://cards.scryfall.io/png/front/9/1/91664e04-b4e1-4638-8194-6c373ecd02d9.png?1715954802", "art_crop": "https://cards.scryfall.io/art_crop/front/9/1/91664e04-b4e1-4638-8194-6c373ecd02d9.jpg?1715954802", "border_crop": "https://cards.scryfall.io/border_crop/front/9/1/91664e04-b4e1-4638-8194-6c373ecd02d9.jpg?1715954802"}}, {"object": "card_face", "name": "Eriette, the Beguiler", "mana_cost": "", "type_line": "Card", "oracle_text": "", "colors": [], "artist": "Dibujante Nocturno", "artist_id": "ed4f7e1b-4139-4e17-a671-442ce49eb775", "illustration_id": "46dc3351-c61e-45c7-8d8d-ddecd000a659", "image_uris": {"small": "https://cards.scryfall.io/small/back/9/1/91664e04-b4e1-4638-8194-6c373ecd02d9.jpg?1715954802", "normal": "https://cards.scryfall.io/normal/back/9/1/91664e04-b4e1-4638-8194-6c373ecd02d9.jpg?1715954802", "large": "https://cards.scryfall.io/large/back/9/1/91664e04-b4e1-4638-8194-6c373ecd02d9.jpg?1715954802", "png": "https://cards.scryfall.io/png/back/9/1/91664e04-b4e1-4638-8194-6c373ecd02d9.png?1715954802", "art_crop": "https://cards.scryfall.io/art_crop/back/9/1/91664e04-b4e1-4638-8194-6c373ecd02d9.jpg?1715954802", "border_crop": "https://cards.scryfall.io/border_crop/back/9/1/91664e04-b4e1-4638-8194-6c373ecd02d9.jpg?1715954802"}}], "legalities": {"standard": "not_legal", "future": "not_legal", "historic": "not_legal", "timeless": "not_legal", "gladiator": "not_legal", "pioneer": "not_legal", "modern": "not_legal", "legacy": "not_legal", "pauper": "not_legal", "vintage": "not_legal", "penny": "not_legal", "commander": "not_legal", "oathbreaker": "not_legal", "standardbrawl": "not_legal", "brawl": "not_legal", "alchemy": "not_legal", "paupercommander": "not_legal", "duel": "not_legal", "oldschool": "not_legal", "premodern": "not_legal", "predh": "not_legal"}, "games": ["paper"], "reserved": false, "game_changer": false, "foil": true, "nonfoil": true, "finishes": ["nonfoil", "foil"], "oversized": false, "promo": false, "reprint": false, "variation": false, "set_id": "9d2325c7-06a4-4404-8bbf-1fcdf02f15ac", "set": "aotj", "set_name": "Outlaws of Thunder Junction Art Series", "set_type": "memorabilia", "set_uri": "https://api.scryfall.com/sets/9d2325c7-06a4-4404-8bbf-1fcdf02f15ac", "set_search_uri": "https://api.scryfall.com/cards/search?order=set&q=e%3Aaotj&unique=prints", "scryfall_set_uri": "https://scryfall.com/sets/aotj?utm_source=api", "rulings_uri": "https://api.scryfall.com/cards/91664e04-b4e1-4638-8194-6c373ecd02d9/rulings", "prints_search_uri": "https://api.scryfall.com/cards/search?order=released&q=oracleid%3A0a2995ff-5623-44d7-8620-18f695903d9a&unique=prints", "collector_number": "52", "digital": false, "rarity": "common", "artist": "Dibujante Nocturno", "artist_ids": ["ed4f7e1b-4139-4e17-a671-442ce49eb775"], "border_color": "borderless", "frame": "2015", "full_art": false, "textless": false, "booster": false, "story_spotlight": false, "prices": {"usd": null, "usd_foil": null, "usd_etched": null, "eur": null, "eur_foil": null, "tix": null}, "related_uris": {"tcgplayer_infinite_articles": "https://partner.tcgplayer.com/c/4931599/1830156/21018?subId1=api&trafcat=tcgplayer.com%2Fsearch%2Farticles&u=https%3A%2F%2Fwww.tcgplayer.com%2Fsearch%2Farticles%3FproductLineName%3Dmagic%26q%3DEriette%252C%2Bthe%2BBeguiler%2B%252F%252F%2BEriette%252C%2Bthe%2BBeguiler", "tcgplayer_infinite_decks": "https://partner.tcgplayer.com/c/4931599/1830156/21018?subId1=api&trafcat=tcgplayer.com%2Fsearch%2Fdecks&u=https%3A%2F%2Fwww.tcgplayer.com%2Fsearch%2Fdecks%3FproductLineName%3Dmagic%26q%3DEriette%252C%2Bthe%2BBeguiler%2B%252F%252F%2BEriette%252C%2Bthe%2BBeguiler", "edhrec": "https://edhrec.com/route/?cc=Eriette%2C+the+Beguiler"}, "purchase_uris": {"tcgplayer": "https://partner.tcgplayer.com/c/4931599/1830156/21018?subId1=api&u=https%3A%2F%2Fwww.tcgplayer.com%2Fsearch%2Fmagic%2Fproduct%3FproductLineName%3Dmagic%26q%3DEriette%252C%2Bthe%2BBeguiler%26view%3Dgrid", "cardmarket": "https://www.cardmarket.com/en/Magic/Products/Search?referrer=scryfall&searchString=Eriette%2C+the+Beguiler&utm_campaign=card_prices&utm_medium=text&utm_source=scryfall", "cardhoarder": "https://www.cardhoarder.com/cards?affiliate_id=scryfall&data%5Bsearch%5D=Eriette%2C+the+Beguiler&ref=card-profile&utm_campaign=affiliate&utm_medium=card&utm_source=scryfall"}}