{"object": "card", "id": "1efbea01-c6a1-4380-a14f-6206c7895e48", "oracle_id": "30c0df75-9822-4016-a52b-d2e69dd58124", "multiverse_ids": [531830], "tcgplayer_id": 243358, "cardmarket_id": 571543, "name": "Galea, Kindler of Hope", "lang": "en", "released_at": "2021-07-23", "uri": "https://api.scryfall.com/cards/1efbea01-c6a1-4380-a14f-6206c7895e48", "scryfall_uri": "https://scryfall.com/card/afc/1/galea-kindler-of-hope?utm_source=api", "layout": "normal", "highres_image": true, "image_status": "highres_scan", "image_uris": {"small": "https://cards.scryfall.io/small/front/1/e/1efbea01-c6a1-4380-a14f-6206c7895e48.jpg?1632335378", "normal": "https://cards.scryfall.io/normal/front/1/e/1efbea01-c6a1-4380-a14f-6206c7895e48.jpg?1632335378", "large": "https://cards.scryfall.io/large/front/1/e/1efbea01-c6a1-4380-a14f-6206c7895e48.jpg?1632335378", "png": "https://cards.scryfall.io/png/front/1/e/1efbea01-c6a1-4380-a14f-6206c7895e48.png?1632335378", "art_crop": "https://cards.scryfall.io/art_crop/front/1/e/1efbea01-c6a1-4380-a14f-6206c7895e48.jpg?1632335378", "border_crop": "https://cards.scryfall.io/border_crop/front/1/e/1efbea01-c6a1-4380-a14f-6206c7895e48.jpg?1632335378"}, "mana_cost": "{1}{G}{W}{U}", "cmc": 4.0, "type_line": "Legendary Creature \u2014 Elf Knight", "oracle_text": "Vigilance\nYou may look at the top card of your library any time.\nYou may cast Aura and Equipment spells from the top of your library. When you cast an Equipment spell this way, it gains \"When this Equipment enters, attach it to target creature you control.\"", "power": "4", "toughness": "4", "colors": ["G", "U", "W"], "color_identity": ["G", "U", "W"], "keywords": ["Vigilance"], "legalities": {"standard": "not_legal", "future": "not_legal", "historic": "not_legal", "timeless": "not_legal", "gladiator": "not_legal", "pioneer": "not_legal", "modern": "not_legal", "legacy": "legal", "pauper": "not_legal", "vintage": "legal", "penny": "not_legal", "commander": "legal", "oathbreaker": "legal", "standardbrawl": "not_legal", "brawl": "not_legal", "alchemy": "not_legal", "paupercommander": "not_legal", "duel": "legal", "oldschool": "not_legal", "premodern": "not_legal", "predh": "not_legal"}, "games": ["paper"], "reserved": false, "game_changer": false, "foil": true, "nonfoil": false, "finishes": ["foil"], "oversized": false, "promo": false, "reprint": false, "variation": false, "set_id": "db1b46f9-893c-4623-9465-985ff6e4472c", "set": "afc", "set_name": "Forgotten Realms Commander", "set_type": "commander", "set_uri": "https://api.scryfall.com/sets/db1b46f9-893c-4623-9465-985ff6e4472c", "set_search_uri": "https://api.scryfall.com/cards/search?order=set&q=e%3Aafc&unique=prints", "scryfall_set_uri": "https://scryfall.com/sets/afc?utm_source=api", "rulings_uri": "https://api.scryfall.com/cards/1efbea01-c6a1-4380-a14f-6206c7895e48/rulings", "prints_search_uri": "https://api.scryfall.com/cards/search?order=released&q=oracleid%3A30c0df75-9822-4016-a52b-d2e69dd58124&unique=prints", "collector_number": "1", "digital": false, "rarity": "mythic", "card_back_id": "0aeebaf5-8c7d-4636-9e82-8c27447861f7", "artist": "Johannes Voss", "artist_ids": ["3593dd7e-c547-4a32-81cd-7da725f60118"], "illustration_id": "cccb165d-1e33-4326-a803-a620aa4eeee7", "border_color": "black", "frame": "2015", "frame_effects": ["legendary"], "security_stamp": "oval", "full_art": false, "textless": false, "booster": false, "story_spotlight": false, "edhrec_rank": 10515, "preview": {"source": "The Command Zone", "source_uri": "https://twitter.com/commandcast/status/1411043182247235585", "previewed_at": "2021-07-02"}, "prices": {"usd": null, "usd_foil": "0.58", "usd_etched": null, "eur": null, "eur_foil": "0.48", "tix": null}, "related_uris": {"gatherer": "https://gatherer.wizards.com/Pages/Card/Details.aspx?multiverseid=531830&printed=false", "tcgplayer_infinite_articles": "https://partner.tcgplayer.com/c/4931599/1830156/21018?subId1=api&trafcat=tcgplayer.com%2Fsearch%2Farticles&u=https%3A%2F%2Fwww.tcgplayer.com%2Fsearch%2Farticles%3FproductLineName%3Dmagic%26q%3DGalea%252C%2BKindler%2Bof%2BHope", "tcgplayer_infinite_decks": "https://partner.tcgplayer.com/c/4931599/1830156/21018?subId1=api&trafcat=tcgplayer.com%2Fsearch%2Fdecks&u=https%3A%2F%2Fwww.tcgplayer.com%2Fsearch%2Fdecks%3FproductLineName%3Dmagic%26q%3DGalea%252C%2BKindler%2Bof%2BHope", "edhrec": "https://edhrec.com/route/?cc=Galea%2C+Kindler+of+Hope"}, "purchase_uris": {"tcgplayer": "https://partner.tcgplayer.com/c/4931599/1830156/21018?subId1=api&u=https%3A%2F%2Fwww.tcgplayer.com%2Fproduct%2F243358%3Fpage%3D1", "cardmarket": "https://www.cardmarket.com/en/Magic/Products?idProduct=571543&referrer=scryfall&utm_campaign=card_prices&utm_medium=text&utm_source=scryfall", "cardhoarder": "https://www.cardhoarder.com/cards?affiliate_id=scryfall&data%5Bsearch%5D=Galea%2C+Kindler+of+Hope&ref=card-profile&utm_campaign=affiliate&utm_medium=card&utm_source=scryfall"}}