{"object": "card", "id": "73e92389-4bd2-492e-b4d6-d7cb6baedc41", "oracle_id": "c4e51cba-e5f7-4f44-9ae9-9223a2efd004", "multiverse_ids": [607182, 607183], "mtgo_id": 110136, "arena_id": 84418, "tcgplayer_id": 490548, "cardmarket_id": 704036, "name": "Harried Artisan // Phyrexian Skyflayer", "lang": "en", "released_at": "2023-04-21", "uri": "https://api.scryfall.com/cards/73e92389-4bd2-492e-b4d6-d7cb6baedc41", "scryfall_uri": "https://scryfall.com/card/mom/143/harried-artisan-phyrexian-skyflayer?utm_source=api", "layout": "transform", "highres_image": true, "image_status": "highres_scan", "cmc": 3.0, "type_line": "Creature \u2014 Human Artificer // Creature \u2014 Phyrexian Artificer", "color_identity": ["R", "W"], "keywords": ["Flying", "Transform", "Haste"], "card_faces": [{"object": "card_face", "name": "Harried Artisan", "mana_cost": "{2}{R}", "type_line": "Creature \u2014 Human Artificer", "oracle_text": "Haste\n{3}{W/P}: Transform this creature. Activate only as a sorcery. ({W/P} can be paid with either {W} or 2 life.)", "colors": ["R"], "power": "2", "toughness": "3", "flavor_text": "As strange portals roared open across Theros, Lydus gathered his prototype and fled. He was so close to perfecting his design.", "artist": "Caio Monteiro", "artist_id": "d5053eb6-af72-47a0-b6e8-023cc3b9aefb", "illustration_id": "4aa7a622-8b98-46db-a336-8f9f3a499ae9", "image_uris": {"small": "https://cards.scryfall.io/small/front/7/3/73e92389-4bd2-492e-b4d6-d7cb6baedc41.jpg?1682204203", "normal": "https://cards.scryfall.io/normal/front/7/3/73e92389-4bd2-492e-b4d6-d7cb6baedc41.jpg?1682204203", "large": "https://cards.scryfall.io/large/front/7/3/73e92389-4bd2-492e-b4d6-d7cb6baedc41.jpg?1682204203", "png": "https://cards.scryfall.io/png/front/7/3/73e92389-4bd2-492e-b4d6-d7cb6baedc41.png?1682204203", "art_crop": "https://cards.scryfall.io/art_crop/front/7/3/73e92389-4bd2-492e-b4d6-d7cb6baedc41.jpg?1682204203", "border_crop": "https://cards.scryfall.io/border_crop/front/7/3/73e92389-4bd2-492e-b4d6-d7cb6baedc41.jpg?1682204203"}}, {"object": "card_face", "name": "Phyrexian Skyflayer", "mana_cost": "", "type_line": "Creature \u2014 Phyrexian Artificer", "oracle_text": "Flying, haste", "colors": ["R", "W"], "color_indicator": ["R", "W"], "power": "3", "toughness": "4", "flavor_text": "Soaring in Realmbreaker's embrace, he finally understood what perfection was.", "artist": "Caio Monteiro", "artist_id": "d5053eb6-af72-47a0-b6e8-023cc3b9aefb", "illustration_id": "5eb5d55b-ebdb-498e-9dd9-db607907d60a", "image_uris": {"small": "https://cards.scryfall.io/small/back/7/3/73e92389-4bd2-492e-b4d6-d7cb6baedc41.jpg?1682204203", "normal": "https://cards.scryfall.io/normal/back/7/3/73e92389-4bd2-492e-b4d6-d7cb6baedc41.jpg?1682204203", "large": "https://cards.scryfall.io/large/back/7/3/73e92389-4bd2-492e-b4d6-d7cb6baedc41.jpg?1682204203", "png": "https://cards.scryfall.io/png/back/7/3/73e92389-4bd2-492e-b4d6-d7cb6baedc41.png?1682204203", "art_crop": "https://cards.scryfall.io/art_crop/back/7/3/73e92389-4bd2-492e-b4d6-d7cb6baedc41.jpg?1682204203", "border_crop": "https://cards.scryfall.io/border_crop/back/7/3/73e92389-4bd2-492e-b4d6-d7cb6baedc41.jpg?1682204203"}}], "legalities": {"standard": "not_legal", "future": "not_legal", "historic": "legal", "timeless": "legal", "gladiator": "legal", "pioneer": "legal", "modern": "legal", "legacy": "legal", "pauper": "not_legal", "vintage": "legal", "penny": "not_legal", "commander": "legal", "oathbreaker": "legal", "standardbrawl": "not_legal", "brawl": "legal", "alchemy": "not_legal", "paupercommander": "not_legal", "duel": "legal", "oldschool": "not_legal", "premodern": "not_legal", "predh": "not_legal"}, "games": ["paper", "arena", "mtgo"], "reserved": false, "game_changer": false, "foil": true, "nonfoil": true, "finishes": ["nonfoil", "foil"], "oversized": false, "promo": false, "reprint": false, "variation": false, "set_id": "392f7315-dc53-40a3-a2cc-5482dbd498b3", "set": "mom", "set_name": "March of the Machine", "set_type": "expansion", "set_uri": "https://api.scryfall.com/sets/392f7315-dc53-40a3-a2cc-5482dbd498b3", "set_search_uri": "https://api.scryfall.com/cards/search?order=set&q=e%3Amom&unique=prints", "scryfall_set_uri": "https://scryfall.com/sets/mom?utm_source=api", "rulings_uri": "https://api.scryfall.com/cards/73e92389-4bd2-492e-b4d6-d7cb6baedc41/rulings", "prints_search_uri": "https://api.scryfall.com/cards/search?order=released&q=oracleid%3Ac4e51cba-e5f7-4f44-9ae9-9223a2efd004&unique=prints", "collector_number": "143", "digital": false, "rarity": "uncommon", "artist": "Caio Monteiro", "artist_ids": ["d5053eb6-af72-47a0-b6e8-023cc3b9aefb"], "border_color": "black", "frame": "2015", "full_art": false, "textless": false, "booster": true, "story_spotlight": false, "edhrec_rank": 25963, "preview": {"source": "ManaCurves", "source_uri": "https://twitter.com/ManaCurves/status/1641477963924353025", "previewed_at": "2023-03-30"}, "prices": {"usd": "0.03", "usd_foil": "0.03", "usd_etched": null, "eur": "0.02", "eur_foil": "0.09", "tix": "0.03"}, "related_uris": {"gatherer": "https://gatherer.wizards.com/Pages/Card/Details.aspx?multiverseid=607182&printed=false", "tcgplayer_infinite_articles": "https://partner.tcgplayer.com/c/4931599/1830156/21018?subId1=api&trafcat=tcgplayer.com%2Fsearch%2Farticles&u=https%3A%2F%2Fwww.tcgplayer.com%2Fsearch%2Farticles%3FproductLineName%3Dmagic%26q%3DHarried%2BArtisan%2B%252F%252F%2BPhyrexian%2BSkyflayer", "tcgplayer_infinite_decks": "https://partner.tcgplayer.com/c/4931599/1830156/21018?subId1=api&trafcat=tcgplayer.com%2Fsearch%2Fdecks&u=https%3A%2F%2Fwww.tcgplayer.com%2Fsearch%2Fdecks%3FproductLineName%3Dmagic%26q%3DHarried%2BArtisan%2B%252F%252F%2BPhyrexian%2BSkyflayer", "edhrec": "https://edhrec.com/route/?cc=Harried+Artisan"}, "purchase_uris": {"tcgplayer": "https://partner.tcgplayer.com/c/4931599/1830156/21018?subId1=api&u=https%3A%2F%2Fwww.tcgplayer.com%2Fproduct%2F490548%3Fpage%3D1", "cardmarket": "https://www.cardmarket.com/en/Magic/Products?idProduct=704036&referrer=scryfall&utm_campaign=card_prices&utm_medium=text&utm_source=scryfall", "cardhoarder": "https://www.cardhoarder.com/cards/110136?affiliate_id=scryfall&ref=card-profile&utm_campaign=affiliate&utm_medium=card&utm_source=scryfall"}}