{"object": "card", "id": "1bb19a35-7224-4fe2-a0c0-17b93d2837ad", "oracle_id": "10e0ccdf-9a31-402a-9fbf-f501ce63fa52", "multiverse_ids": [668412], "mtgo_id": 127604, "tcgplayer_id": 556319, "cardmarket_id": 775562, "name": "Merciless Harlequin", "lang": "en", "released_at": "2024-07-05", "uri": "https://api.scryfall.com/cards/1bb19a35-7224-4fe2-a0c0-17b93d2837ad", "scryfall_uri": "https://scryfall.com/card/acr/287/merciless-harlequin?utm_source=api", "layout": "normal", "highres_image": true, "image_status": "highres_scan", "image_uris": {"small": "https://cards.scryfall.io/small/front/1/b/1bb19a35-7224-4fe2-a0c0-17b93d2837ad.jpg?1721425643", "normal": "https://cards.scryfall.io/normal/front/1/b/1bb19a35-7224-4fe2-a0c0-17b93d2837ad.jpg?1721425643", "large": "https://cards.scryfall.io/large/front/1/b/1bb19a35-7224-4fe2-a0c0-17b93d2837ad.jpg?1721425643", "png": "https://cards.scryfall.io/png/front/1/b/1bb19a35-7224-4fe2-a0c0-17b93d2837ad.png?1721425643", "art_crop": "https://cards.scryfall.io/art_crop/front/1/b/1bb19a35-7224-4fe2-a0c0-17b93d2837ad.jpg?1721425643", "border_crop": "https://cards.scryfall.io/border_crop/front/1/b/1bb19a35-7224-4fe2-a0c0-17b93d2837ad.jpg?1721425643"}, "mana_cost": "{2}{B}", "cmc": 3.0, "type_line": "Creature \u2014 Human Assassin", "oracle_text": "Freerunning {1}{B} (You may cast this spell for its freerunning cost if you dealt combat damage to a player this turn with an Assassin or commander.)\nWhen this creature enters, you draw a card and you lose 1 life.", "power": "2", "toughness": "1", "colors": ["B"], "color_identity": ["B"], "keywords": ["Freerunning"], "legalities": {"standard": "not_legal", "future": "not_legal", "historic": "not_legal", "timeless": "not_legal", "gladiator": "not_legal", "pioneer": "not_legal", "modern": "legal", "legacy": "legal", "pauper": "legal", "vintage": "legal", "penny": "legal", "commander": "legal", "oathbreaker": "legal", "standardbrawl": "not_legal", "brawl": "not_legal", "alchemy": "not_legal", "paupercommander": "legal", "duel": "legal", "oldschool": "not_legal", "premodern": "not_legal", "predh": "not_legal"}, "games": ["paper", "mtgo"], "reserved": false, "game_changer": false, "foil": false, "nonfoil": true, "finishes": ["nonfoil"], "oversized": false, "promo": false, "reprint": false, "variation": false, "set_id": "54b67b0b-cd3f-4e0d-ac25-fef5d966409b", "set": "acr", "set_name": "Assassin's Creed", "set_type": "draft_innovation", "set_uri": "https://api.scryfall.com/sets/54b67b0b-cd3f-4e0d-ac25-fef5d966409b", "set_search_uri": "https://api.scryfall.com/cards/search?order=set&q=e%3Aacr&unique=prints", "scryfall_set_uri": "https://scryfall.com/sets/acr?utm_source=api", "rulings_uri": "https://api.scryfall.com/cards/1bb19a35-7224-4fe2-a0c0-17b93d2837ad/rulings", "prints_search_uri": "https://api.scryfall.com/cards/search?order=released&q=oracleid%3A10e0ccdf-9a31-402a-9fbf-f501ce63fa52&unique=prints", "collector_number": "287", "digital": false, "rarity": "common", "card_back_id": "0aeebaf5-8c7d-4636-9e82-8c27447861f7", "artist": "Lixin Yin", "artist_ids": ["25645c87-71be-400b-8522-618a52c37454"], "illustration_id": "5d4540bc-94fd-4bbb-802e-98209ec2d51a", "border_color": "black", "frame": "2015", "security_stamp": "triangle", "full_art": false, "textless": false, "booster": false, "story_spotlight": false, "edhrec_rank": 11210, "penny_rank": 8799, "prices": {"usd": "0.13", "usd_foil": null, "usd_etched": null, "eur": "0.19", "eur_foil": null, "tix": "0.04"}, "related_uris": {"gatherer": "https://gatherer.wizards.com/Pages/Card/Details.aspx?multiverseid=668412&printed=false", "tcgplayer_infinite_articles": "https://partner.tcgplayer.com/c/4931599/1830156/21018?subId1=api&trafcat=tcgplayer.com%2Fsearch%2Farticles&u=https%3A%2F%2Fwww.tcgplayer.com%2Fsearch%2Farticles%3FproductLineName%3Dmagic%26q%3DMerciless%2BHarlequin", "tcgplayer_infinite_decks": "https://partner.tcgplayer.com/c/4931599/1830156/21018?subId1=api&trafcat=tcgplayer.com%2Fsearch%2Fdecks&u=https%3A%2F%2Fwww.tcgplayer.com%2Fsearch%2Fdecks%3FproductLineName%3Dmagic%26q%3DMerciless%2BHarlequin", "edhrec": "https://edhrec.com/route/?cc=Merciless+Harlequin"}, "purchase_uris": {"tcgplayer": "https://partner.tcgplayer.com/c/4931599/1830156/21018?subId1=api&u=https%3A%2F%2Fwww.tcgplayer.com%2Fproduct%2F556319%3Fpage%3D1", "cardmarket": "https://www.cardmarket.com/en/Magic/Products?idProduct=775562&referrer=scryfall&utm_campaign=card_prices&utm_medium=text&utm_source=scryfall", "cardhoarder": "https://www.cardhoarder.com/cards/127604?affiliate_id=scryfall&ref=card-profile&utm_campaign=affiliate&utm_medium=card&utm_source=scryfall"}}