{"object": "card", "id": "660d8e43-13e1-464b-b251-c7c2d77732ca", "oracle_id": "dd85fcd6-9bfd-4deb-a56a-77c6bca8eb97", "multiverse_ids": [], "name": "Squid", "lang": "en", "released_at": "2025-06-13", "uri": "https://api.scryfall.com/cards/660d8e43-13e1-464b-b251-c7c2d77732ca", "scryfall_uri": "https://scryfall.com/card/tfic/5/squid?utm_source=api", "layout": "token", "highres_image": true, "image_status": "highres_scan", "image_uris": {"small": "https://cards.scryfall.io/small/front/6/6/660d8e43-13e1-464b-b251-c7c2d77732ca.jpg?1749245683", "normal": "https://cards.scryfall.io/normal/front/6/6/660d8e43-13e1-464b-b251-c7c2d77732ca.jpg?1749245683", "large": "https://cards.scryfall.io/large/front/6/6/660d8e43-13e1-464b-b251-c7c2d77732ca.jpg?1749245683", "png": "https://cards.scryfall.io/png/front/6/6/660d8e43-13e1-464b-b251-c7c2d77732ca.png?1749245683", "art_crop": "https://cards.scryfall.io/art_crop/front/6/6/660d8e43-13e1-464b-b251-c7c2d77732ca.jpg?1749245683", "border_crop": "https://cards.scryfall.io/border_crop/front/6/6/660d8e43-13e1-464b-b251-c7c2d77732ca.jpg?1749245683"}, "mana_cost": "", "cmc": 0.0, "type_line": "Token Creature \u2014 Squid", "oracle_text": "Islandwalk (This creature can't be blocked as long as defending player controls an Island.)", "power": "1", "toughness": "1", "colors": ["U"], "color_identity": ["U"], "keywords": ["Landwalk", "Islandwalk"], "all_parts": [{"object": "related_card", "id": "886ce333-44d7-458e-a3bb-a58d1d7fc69b", "component": "combo_piece", "name": "Chasm Skulker", "type_line": "Creature \u2014 Squid Horror", "uri": "https://api.scryfall.com/cards/886ce333-44d7-458e-a3bb-a58d1d7fc69b"}, {"object": "related_card", "id": "660d8e43-13e1-464b-b251-c7c2d77732ca", "component": "token", "name": "Squid", "type_line": "Token Creature \u2014 Squid", "uri": "https://api.scryfall.com/cards/660d8e43-13e1-464b-b251-c7c2d77732ca"}, {"object": "related_card", "id": "f34cd305-d823-4996-9f8f-806386491f5d", "component": "combo_piece", "name": "Coral Barrier", "type_line": "Creature \u2014 Wall", "uri": "https://api.scryfall.com/cards/f34cd305-d823-4996-9f8f-806386491f5d"}], "legalities": {"standard": "not_legal", "future": "not_legal", "historic": "not_legal", "timeless": "not_legal", "gladiator": "not_legal", "pioneer": "not_legal", "modern": "not_legal", "legacy": "not_legal", "pauper": "not_legal", "vintage": "not_legal", "penny": "not_legal", "commander": "not_legal", "oathbreaker": "not_legal", "standardbrawl": "not_legal", "brawl": "not_legal", "alchemy": "not_legal", "paupercommander": "not_legal", "duel": "not_legal", "oldschool": "not_legal", "premodern": "not_legal", "predh": "not_legal"}, "games": ["paper", "mtgo", "arena"], "reserved": false, "game_changer": false, "foil": true, "nonfoil": true, "finishes": ["nonfoil", "foil"], "oversized": false, "promo": false, "reprint": true, "variation": false, "set_id": "40f74ca2-e802-4278-ba9d-5fb5da32e2ab", "set": "tfic", "set_name": "Final Fantasy Commander Tokens", "set_type": "token", "set_uri": "https://api.scryfall.com/sets/40f74ca2-e802-4278-ba9d-5fb5da32e2ab", "set_search_uri": "https://api.scryfall.com/cards/search?order=set&q=e%3Atfic&unique=prints", "scryfall_set_uri": "https://scryfall.com/sets/tfic?utm_source=api", "rulings_uri": "https://api.scryfall.com/cards/660d8e43-13e1-464b-b251-c7c2d77732ca/rulings", "prints_search_uri": "https://api.scryfall.com/cards/search?order=released&q=oracleid%3Add85fcd6-9bfd-4deb-a56a-77c6bca8eb97&unique=prints", "collector_number": "5", "digital": false, "rarity": "common", "card_back_id": "0aeebaf5-8c7d-4636-9e82-8c27447861f7", "artist": "Daniel Correia", "artist_ids": ["d383f00d-0078-4c43-92f6-cbf62ab5df05"], "illustration_id": "036cf08f-1104-490f-bac5-a7cff71cfc95", "border_color": "black", "frame": "2015", "security_stamp": "triangle", "full_art": false, "textless": false, "booster": false, "story_spotlight": false, "promo_types": ["surgefoil", "ffx"], "prices": {"usd": null, "usd_foil": null, "usd_etched": null, "eur": null, "eur_foil": null, "tix": null}, "related_uris": {"tcgplayer_infinite_articles": "https://partner.tcgplayer.com/c/4931599/1830156/21018?subId1=api&trafcat=tcgplayer.com%2Fsearch%2Farticles&u=https%3A%2F%2Fwww.tcgplayer.com%2Fsearch%2Farticles%3FproductLineName%3Dmagic%26q%3DSquid", "tcgplayer_infinite_decks": "https://partner.tcgplayer.com/c/4931599/1830156/21018?subId1=api&trafcat=tcgplayer.com%2Fsearch%2Fdecks&u=https%3A%2F%2Fwww.tcgplayer.com%2Fsearch%2Fdecks%3FproductLineName%3Dmagic%26q%3DSquid", "edhrec": "https://edhrec.com/route/?cc=Squid"}, "purchase_uris": {"tcgplayer": "https://partner.tcgplayer.com/c/4931599/1830156/21018?subId1=api&u=https%3A%2F%2Fwww.tcgplayer.com%2Fsearch%2Fmagic%2Fproduct%3FproductLineName%3Dmagic%26q%3DSquid%26view%3Dgrid", "cardmarket": "https://www.cardmarket.com/en/Magic/Products/Search?referrer=scryfall&searchString=Squid&utm_campaign=card_prices&utm_medium=text&utm_source=scryfall", "cardhoarder": "https://www.cardhoarder.com/cards?affiliate_id=scryfall&data%5Bsearch%5D=Squid&ref=card-profile&utm_campaign=affiliate&utm_medium=card&utm_source=scryfall"}}